cnpjgenerator/__init__.py
cnpjgenerator/library.py
cnpjgenerator/utils.py
robotframework_cnpjgenerator-1.0.0.dist-info/METADATA
robotframework_cnpjgenerator-1.0.0.dist-info/WHEEL
robotframework_cnpjgenerator-1.0.0.dist-info/top_level.txt
robotframework_cnpjgenerator-1.0.0.dist-info/RECORD
